{
  "project_info": {
    "project_number": "384082929086",
    "project_id": "chatapp-c68bc",
    "storage_bucket": "chatapp-c68bc.appspot.com"
  },
  "client": [
    {
      "client_info": {
        "mobilesdk_app_id": "1:384082929086:android:c164a8845d1a4256b505ef",
        "android_client_info": {
          "package_name": "com.example.chatapp"
        }
      },
      "oauth_client": [],
      "api_key": [
        {
          "current_key": "AIzaSyBK0Sm65TAKAZ3YS6MhztWUVbgGlCbnT50"
        }
      ],
      "services": {
        "appinvite_service": {
          "other_platform_oauth_client": []
        }
      }
    }
  ],
  "configuration_version": "1"
}